snowcell/__about__.py
snowcell/__init__.py
snowcell/chat.py
snowcell/client.py
snowcell/completion.py
snowcell/exceptions.py
snowcell/py.typed
snowcell/schemas/__init__.py
snowcell/schemas/chat.py
snowcell/schemas/common.py
snowcell/schemas/completion.py
snowcell-0.1.0.dist-info/licenses/LICENSE
snowcell-0.1.0.dist-info/METADATA
snowcell-0.1.0.dist-info/WHEEL
snowcell-0.1.0.dist-info/top_level.txt
snowcell-0.1.0.dist-info/RECORD
