Metadata-Version: 2.4
Name: snowcell
Version: 0.1.0
Summary: Python SDK for Snowcell inference
Author: Snowcell
License: MIT License
Project-URL: Homepage, https://github.com/snowcell-cloud/sdk-python
Project-URL: Repository, https://github.com/snowcell-cloud/sdk-python
Classifier: Development Status :: 3 - Alpha
Classifier: Programming Language :: Python :: 3
Classifier: License :: OSI Approved :: MIT License
Requires-Python: >=3.9
License-File: LICENSE
Requires-Dist: httpx<0.29,>=0.27
Requires-Dist: pydantic<3,>=2
Requires-Dist: typing-extensions>=4.8; python_version < "3.11"
Dynamic: license-file
